restrunner/__init__.py
restrunner/app.py
restrunner/common/__init__.py
restrunner/common/cmd.py
restrunner/common/data.py
restrunner/common/db.py
restrunner/conf/__init__.py
restrunner/conf/settings.py
restrunner/resources/__init__.py
restrunner/resources/query.py
restrunner/resources/restrunner.py
RestRunner-0.0.6.dist-info/LICENSE
RestRunner-0.0.6.dist-info/METADATA
RestRunner-0.0.6.dist-info/WHEEL
RestRunner-0.0.6.dist-info/top_level.txt
RestRunner-0.0.6.dist-info/RECORD
