Metadata-Version: 2.1
Name: RestRunner
Version: 0.0.6
Summary: A tool for run linux command with flask rest api.
Author-email: Yusuf Düzgün <yzduzgun@gmail.com>
Project-URL: Homepage, https://github.com/ysfduzgun/restrunner
Project-URL: Bug Tracker, https://github.com/ysfduzgun/restrunner/issues
Classifier: Programming Language :: Python :: 3
Classifier: License :: OSI Approved :: MIT License
Classifier: Operating System :: OS Independent
Requires-Python: >=3.7
License-File: LICENSE
Requires-Dist: Flask
Requires-Dist: Flask-RESTful
Requires-Dist: tinydb
